easy_whitelist/__init__.py
easy_whitelist/__main__.py
easy_whitelist/_core.py
easy_whitelist/config/__init__.py
easy_whitelist/config/arg.py
easy_whitelist/config/log.py
easy_whitelist/ip_detector/__init__.py
easy_whitelist/ip_detector/detectors.py
easy_whitelist/ip_detector/utils.py
easy_whitelist/tcloud/__init__.py
easy_whitelist/tcloud/client.py
easy_whitelist/tcloud/core.py
easy_whitelist/tcloud/ls_template.py
easy_whitelist/tcloud/template.py
mypkg_hello-1.0.90.dist-info/licenses/LICENSE
mypkg_hello-1.0.90.dist-info/METADATA
mypkg_hello-1.0.90.dist-info/WHEEL
mypkg_hello-1.0.90.dist-info/top_level.txt
mypkg_hello-1.0.90.dist-info/RECORD
